mcp_database_reader/server.py
mcp_database_reader/database/connector.py
mcp_database_reader/database/queries.py
mcp_database_reader/tools/database_tools.py
mcp_database_reader-0.1.0.dist-info/METADATA
mcp_database_reader-0.1.0.dist-info/WHEEL
mcp_database_reader-0.1.0.dist-info/entry_points.txt
mcp_database_reader-0.1.0.dist-info/top_level.txt
mcp_database_reader-0.1.0.dist-info/RECORD
